ccid/VERSION
ccid/__init__.py
ccid/cli/__init__.py
ccid-0.0.1.dist-info/entry_points.txt
ccid-0.0.1.dist-info/LICENSE-APACHE
ccid-0.0.1.dist-info/LICENSE-MIT
ccid-0.0.1.dist-info/WHEEL
ccid-0.0.1.dist-info/METADATA
ccid-0.0.1.dist-info/RECORD
