Metadata-Version: 2.1
Name: ccid
Version: 0.0.1
Summary: Python library for SoloKeys.
Home-page: https://github.com/solokeys/ccid
License: UNKNOWN
Author: SoloKeys
Author-email: hello@solokeys.com
Requires-Python: >=3.6
Classifier: License :: OSI Approved :: MIT License
Classifier: License :: OSI Approved :: Apache Software License
Classifier: Intended Audience :: Developers
Classifier: Intended Audience :: End Users/Desktop
Classifier: Programming Language :: Python :: 3 :: Only
Classifier: Programming Language :: Python :: 3.6
Classifier: Programming Language :: Python :: 3.7
Requires-Dist: click >= 7.0
